Metadata-Version: 2.1
Name: coopdigital-jsonschema
Version: 2.6.0
Summary: An implementation of JSON Schema validation for Python
Home-page: http://github.com/Julian/jsonschema
Author: Julian Berman
Author-email: Julian@GrayVines.com
Maintainer: Olivia Mackintosh
Maintainer-email: olivia.mackintosh@coopdigital.co.uk
License: MIT
Platform: UNKNOWN
Classifier: Development Status :: 5 - Production/Stable
Classifier: Intended Audience :: Developers
Classifier: License :: OSI Approved :: MIT License
Classifier: Operating System :: OS Independent
Classifier: Programming Language :: Python
Classifier: Programming Language :: Python :: 2
Classifier: Programming Language :: Python :: 2.7
Classifier: Programming Language :: Python :: 3
Classifier: Programming Language :: Python :: 3.5
Classifier: Programming Language :: Python :: Implementation :: CPython
Classifier: Programming Language :: Python :: Implementation :: PyPy
Provides-Extra: format
Requires-Dist: functools32; python_version=='2.7'
Provides-Extra: format
Requires-Dist: rfc3987; extra == 'format'
Requires-Dist: strict-rfc3339; extra == 'format'
Requires-Dist: webcolors; extra == 'format'
